{"moves": [[7, 7], [5, 9], [4, 11], [4, 12], [2, 11], [4, 14], [6, 11], [7, 6], [7, 5], [7, 3], [3, 7], [3, 6], [3, 5], [8, 11], [9, 12], [11, 12], [8, 2], [10, 2], [12, 4], [12, 5], [10, 10], [3, 3], [12, 6], [11, 8], [2, 2], [1, 2], [7, 4], [2, 9], [12, 12], [13, 12], [12, 8], [12, 3], [13, 2], [2, 12], [2, 3], [2, 4], [1, 7], [5, 5], [9, 2], [12, 2], [5, 7], [13, 8], [11, 2], [9, 4], [1, 11], [8, 1], [6, 2], [4, 2], [2, 1], [8, 12], [9, 13], [9, 14], [12, 13], [1, 9], [9, 8], [8, 8], [11, 7], [10, 8], [12, 10], [12, 14], [8, 10], [2, 0], [4, 1], [4, 0], [7, 13], [9, 10], [0, 2], [1, 6], [1, 8], [13, 1], [6, 9], [7, 14], [8, 0], [1, 13], [14, 13], [6, 8], [7, 8], [11, 6], [9, 5], [7, 10], [4, 9], [7, 12], [0, 5], [10, 9]], "result": -1, "metadata": {"game_id": 669, "n_moves": 84, "total_time": 102.0, "avg_move_time": 1.214, "max_depth": 3, "strategy": "mixed", "timestamp": "2025-10-12 07:05:57"}}