{"moves": [[7, 7], [5, 7], [4, 6], [4, 4], [2, 2], [9, 7], [3, 0], [2, 3], [3, 4], [2, 8], [11, 5], [4, 3], [11, 9], [12, 4], [4, 10], [10, 10], [9, 10], [4, 11], [4, 12], [12, 10], [10, 12], [8, 12], [8, 10], [3, 12], [2, 12], [9, 3], [7, 2], [2, 13], [1, 4], [0, 11], [7, 6], [6, 2], [5, 3], [8, 9], [7, 12], [6, 12], [5, 12], [11, 12], [9, 12], [7, 5], [8, 2], [0, 4], [12, 2], [12, 1], [13, 2], [8, 1], [12, 13], [12, 14], [13, 9], [12, 8], [10, 2], [7, 14], [1, 8], [14, 2], [3, 8], [3, 6], [13, 5], [11, 2], [2, 6], [1, 7], [5, 5], [4, 9], [1, 12], [1, 10], [6, 9], [6, 10], [10, 3], [11, 4], [9, 5], [7, 4], [12, 12], [13, 12], [6, 4], [3, 1], [7, 3]], "result": 1, "metadata": {"game_id": 563, "n_moves": 75, "total_time": 87.78, "avg_move_time": 1.17, "max_depth": 3, "strategy": "mixed", "timestamp": "2025-10-12 06:23:44"}}